{
    "_ProgramID": "5943",
    "_ArticleNumber": "RSCAS262000",
    "CategoryPath": {
        "ProductCategoryID": "34036141",
        "ProductCategoryPath": "Running > Chaussures de running"
    },
    "Price": {
        "DisplayPrice": "41.90 EUR"
    },
    "Deeplinks": {
        "Product": "http://clic.reussissonsensemble.fr/click.asp?ref=345425&site=5943&type=text&tnb=23&diurl=http://www.keller-sports.fr/index.php?cl=details&anid=RSCAS2620002&utm_source=fr.affili.net&utm_medium=CPO&utm_term=RSCAS262000"
    },
    "Details": {
        "Title": "Asics - GT-1000 GS Junior",
        "DescriptionShort": "Un excellent rapport qualit\u00e9-prix.Le GT-1000 chaussure de course Asics pour Junior repr\u00e9sente un amorti parfait \u00e0 chaque course! GT-1000 est le nouveau nom de"
    },
    "Date": [

    ],
    "Images": {
        "Img": {
            "_Name": "Adv",
            "URL": "http://i1.keller-sports.fr/out/pictures/1/274-asics-gt-1000-gs-junior-laufschuh-blau-w-rscas262-1_p1.jpg"
        }
    },
    "Properties": {
        "Property": [
            {
                "_Title": "Delivery",
                "_Text": "2-3"
            },
            {
                "_Title": "Gender",
                "_Text": "Enfants"
            },
            {
                "_Title": "Couleur",
                "_Text": "bleu"
            },
            {
                "_Title": "Material",
                "_Text": ""
            },
            {
                "_Title": "Ind_description",
                "_Text": ""
            },
            {
                "_Title": "Category_Single",
                "_Text": "Chaussures de running"
            },
            {
                "_Title": "Avaibility",
                "_Text": "In Stock"
            },
            {
                "_Title": "Stock",
                "_Text": "3"
            },
            {
                "_Title": "Pro_Player",
                "_Text": ""
            },
            {
                "_Title": "New_Product",
                "_Text": ""
            }
        ]
    },
    "Shipping": [

    ],
    "BasePriceInformation": [

    ]
}